randtools/__init__.py
randtools_test-0.9.25.dist-info/METADATA
randtools_test-0.9.25.dist-info/WHEEL
randtools_test-0.9.25.dist-info/top_level.txt
randtools_test-0.9.25.dist-info/RECORD
