Metadata-Version: 2.4
Name: randtools-test
Version: 0.9.25
Summary: A Python module for generating random data with various features including random integers, letters, ASCII characters, bytes, floats, booleans, and URLs
Home-page: 
Author: Creative Star Studio
Author-email: qu20121118@yeah.net
License: BSD 3-Clause License
Requires-Dist: ping3
Dynamic: author
Dynamic: author-email
Dynamic: license
Dynamic: requires-dist
Dynamic: summary
